avn/8D_trained_embedding_model.pth
avn/__init__.py
avn/acoustics.py
avn/avn.py
avn/dataloading.py
avn/plotting.py
avn/segmentation.py
avn/similarity.py
avn/syntax.py
avn/timing.py
avn-0.5.2.dist-info/LICENSE
avn-0.5.2.dist-info/METADATA
avn-0.5.2.dist-info/WHEEL
avn-0.5.2.dist-info/RECORD
