Metadata-Version: 2.1
Name: avn
Version: 0.5.2
Summary: Package for zebra finch song analysis.
Home-page: https://github.com/theresekoch/avn
License: GNU General Public License v3.0
Author: Therese Koch
Requires-Python: >=3.8,<3.10
Classifier: License :: Other/Proprietary License
Classifier: Programming Language :: Python :: 3
Classifier: Programming Language :: Python :: 3.8
Classifier: Programming Language :: Python :: 3.9
Requires-Dist: librosa (==0.10.2)
Requires-Dist: matplotlib (>=3.4.1,<4.0.0)
Requires-Dist: more_itertools (>=8.5.0,<9.0.0)
Requires-Dist: numpy (>=1.20.2,<1.24)
Requires-Dist: pandas (>=1.3.3)
Requires-Dist: scikit-learn (>=0.24.2,<0.25.0)
Requires-Dist: scipy (>=1.6.3,<2.0.0)
Requires-Dist: seaborn (>=0.13.1,<0.14.0)
Project-URL: Documentation, https://avn.readthedocs.io/en/latest/
Project-URL: Repository, https://github.com/theresekoch/avn
